{
    "sites": [
        {
            "site_id": 1,
            "latitude": 17.704859272213792,
            "longitude": 82.08408195698358,
            "composition": "iron"
        },
        {
            "site_id": 2,
            "latitude": 17.12017912555381,
            "longitude": 83.07663813675332,
            "composition": "stony"
        },
        {
            "site_id": 3,
            "latitude": 17.030957269713774,
            "longitude": 83.1859554291181,
            "composition": "stony-iron"
        },
        {
            "site_id": 4,
            "latitude": 17.00165733894302,
            "longitude": 82.15220373439654,
            "composition": "stony"
        },
        {
            "site_id": 5,
            "latitude": 17.531945054764655,
            "longitude": 82.31994203886147,
            "composition": "stony"
        }
    ]
}